solarcell/__init__.py
solarcell/solarcell.py
solarcell-0.2.0.dist-info/LICENSE
solarcell-0.2.0.dist-info/METADATA
solarcell-0.2.0.dist-info/WHEEL
solarcell-0.2.0.dist-info/RECORD
