Metadata-Version: 2.1
Name: solarcell
Version: 0.2.0
Summary: Estimate IV- and PV-curves given photovoltaic cell datasheet parameters.
Home-page: https://github.com/amosborne/solarcell
License: MIT
Keywords: solar,photovoltaic
Author: Alexander Osborne
Author-email: alex@osborneee.com
Requires-Python: >=3.11,<4.0
Classifier: License :: OSI Approved :: MIT License
Classifier: Programming Language :: Python :: 3
Classifier: Programming Language :: Python :: 3.11
Classifier: Topic :: Scientific/Engineering
Requires-Dist: numpy (>=1.26.2,<2.0.0)
Requires-Dist: scipy (>=1.11.4,<2.0.0)
Project-URL: Repository, https://github.com/amosborne/solarcell
